Metadata-Version: 2.1
Name: twarc-edits
Version: 0.0.1
Summary: Find edited tweetes
Home-page: https://github.com/docnow/twarc-edits
Author: Ed Summers
Author-email: ehs@pobox.com
License: MIT
Platform: UNKNOWN
Classifier: License :: OSI Approved :: MIT License
Requires-Python: >=3.3
License-File: LICENSE
